{"inkVersion":20,"root":[["^You got the purple-lollipop!","\n","^Mars can create magic boxes with he magic.","\n","^But only one at a time!","\n","^Try using these boxes to reach higer places or jump further.","\n","^Just press \"C\" or \"2\" to create one! ",{"->":"question"},"\n",["done",{"#f":5,"#n":"g-0"}],null],"done",{"question":[["^Are you ready to continue?","\n","ev","str","^Magic what?","/str","/ev",{"*":".^.c-0","flg":20},"ev","str","^Yes!","/str","/ev",{"*":".^.c-1","flg":20},{"c-0":["\n","^Press \"C\" or \"2\" to use Mars' power and create a box.","\n","^You can create only one at a time.","\n","^Jump on the box, it will be fun!","\n",{"->":".^.^.^"},{"#f":5}],"c-1":["\n","^Ok!","\n","end",{"#f":5}]}],{"#f":1}],"#f":1}],"listDefs":{}}